web_texting/__init__.py
web_texting/configuration.py
web_texting/opeeration_wrapper.py
web_texting/operation.py
web_texting/operation_executor.py
web_texting/rpt_tpl.py
web_texting/unitest_job.py
web_texting/web_job.py
web_texting/web_rpt.py
web_texting-1.2.1.dist-info/METADATA
web_texting-1.2.1.dist-info/WHEEL
web_texting-1.2.1.dist-info/top_level.txt
web_texting-1.2.1.dist-info/RECORD
