Metadata-Version: 2.1
Name: web-texting
Version: 1.2.1
Summary: A Web test module
Home-page: https://github.com/lishimeng/web_texting
Author: li shimeng
Author-email: 316527907@qq.com
License: UNKNOWN
Project-URL: Source, https://github.com/lishimeng/web_texting
Platform: UNKNOWN
Requires-Dist: selenium
Requires-Dist: bottle
